{
  "version": "1.0",
  "timestamp": 1778613541.294902,
  "snapshot_id": "SNAPO-604409cb",
  "cycle": 260,
  "desires": [
    {
      "id": "DES-0",
      "need": "CURIOSITY",
      "desc": "Knowledge coverage 32%. Investigate.",
      "intensity": 0.6799999999999999,
      "urgency": 0.3,
      "fulfilled": true,
      "pressure": 0.408
    },
    {
      "id": "DES-0",
      "need": "AGENCY",
      "desc": "3 failed actions. Expand capability.",
      "intensity": 1,
      "urgency": 0.4,
      "fulfilled": true,
      "pressure": 0.8
    },
    {
      "id": "DES-2",
      "need": "CURIOSITY",
      "desc": "Knowledge coverage 39%. Investigate.",
      "intensity": 0.6100000000000001,
      "urgency": 0.3,
      "fulfilled": false,
      "pressure": 0.36600000000000005
    },
    {
      "id": "DES-2",
      "need": "COHERENCE",
      "desc": "1 falsified beliefs. Resolve.",
      "intensity": 0.2,
      "urgency": 0.5,
      "fulfilled": false,
      "pressure": 0.2
    },
    {
      "id": "DES-2",
      "need": "AGENCY",
      "desc": "2 failed actions. Expand capability.",
      "intensity": 0.6666666666666666,
      "urgency": 0.4,
      "fulfilled": true,
      "pressure": 0.5333333333333333
    },
    {
      "id": "DES-5",
      "need": "CURIOSITY",
      "desc": "Knowledge coverage 46%. Investigate.",
      "intensity": 0.54,
      "urgency": 0.3,
      "fulfilled": false,
      "pressure": 0.324
    },
    {
      "id": "DES-5",
      "need": "COHERENCE",
      "desc": "1 falsified beliefs. Resolve.",
      "intensity": 0.2,
      "urgency": 0.5,
      "fulfilled": false,
      "pressure": 0.2
    },
    {
      "id": "DES-5",
      "need": "AGENCY",
      "desc": "1 failed actions. Expand capability.",
      "intensity": 0.3333333333333333,
      "urgency": 0.4,
      "fulfilled": false,
      "pressure": 0.26666666666666666
    },
    {
      "id": "DES-8",
      "need": "CURIOSITY",
      "desc": "Knowledge coverage 53%. Investigate.",
      "intensity": 0.47,
      "urgency": 0.3,
      "fulfilled": false,
      "pressure": 0.282
    },
    {
      "id": "DES-8",
      "need": "COHERENCE",
      "desc": "2 falsified beliefs. Resolve.",
      "intensity": 0.4,
      "urgency": 0.5,
      "fulfilled": true,
      "pressure": 0.4
    },
    {
      "id": "DES-10",
      "need": "CURIOSITY",
      "desc": "Knowledge coverage 60%. Investigate.",
      "intensity": 0.4,
      "urgency": 0.3,
      "fulfilled": false,
      "pressure": 0.24
    },
    {
      "id": "DES-10",
      "need": "COHERENCE",
      "desc": "2 falsified beliefs. Resolve.",
      "intensity": 0.4,
      "urgency": 0.5,
      "fulfilled": true,
      "pressure": 0.4
    },
    {
      "id": "DES-12",
      "need": "CURIOSITY",
      "desc": "Knowledge coverage 67%. Investigate.",
      "intensity": 0.32999999999999996,
      "urgency": 0.3,
      "fulfilled": false,
      "pressure": 0.19799999999999998
    },
    {
      "id": "DES-12",
      "need": "COHERENCE",
      "desc": "2 falsified beliefs. Resolve.",
      "intensity": 0.4,
      "urgency": 0.5,
      "fulfilled": true,
      "pressure": 0.4
    },
    {
      "id": "DES-14",
      "need": "CURIOSITY",
      "desc": "Knowledge coverage 74%. Investigate.",
      "intensity": 0.2599999999999999,
      "urgency": 0.3,
      "fulfilled": false,
      "pressure": 0.15599999999999994
    },
    {
      "id": "DES-14",
      "need": "COHERENCE",
      "desc": "3 falsified beliefs. Resolve.",
      "intensity": 0.6,
      "urgency": 0.5,
      "fulfilled": true,
      "pressure": 0.6
    },
    {
      "id": "DES-16",
      "need": "COHERENCE",
      "desc": "3 falsified beliefs. Resolve.",
      "intensity": 0.6,
      "urgency": 0.5,
      "fulfilled": true,
      "pressure": 0.6
    },
    {
      "id": "DES-17",
      "need": "COHERENCE",
      "desc": "3 falsified beliefs. Resolve.",
      "intensity": 0.6,
      "urgency": 0.5,
      "fulfilled": true,
      "pressure": 0.6
    },
    {
      "id": "DES-18",
      "need": "COHERENCE",
      "desc": "3 falsified beliefs. Resolve.",
      "intensity": 0.6,
      "urgency": 0.5,
      "fulfilled": true,
      "pressure": 0.6
    },
    {
      "id": "DES-19",
      "need": "COHERENCE",
      "desc": "3 falsified beliefs. Resolve.",
      "intensity": 0.6,
      "urgency": 0.5,
      "fulfilled": true,
      "pressure": 0.6
    },
    {
      "id": "DES-20",
      "need": "COHERENCE",
      "desc": "3 falsified beliefs. Resolve.",
      "intensity": 0.6,
      "urgency": 0.5,
      "fulfilled": true,
      "pressure": 0.6
    },
    {
      "id": "DES-21",
      "need": "COHERENCE",
      "desc": "3 falsified beliefs. Resolve.",
      "intensity": 0.6,
      "urgency": 0.5,
      "fulfilled": true,
      "pressure": 0.6
    },
    {
      "id": "DES-22",
      "need": "COHERENCE",
      "desc": "4 falsified beliefs. Resolve.",
      "intensity": 0.8,
      "urgency": 0.5,
      "fulfilled": true,
      "pressure": 0.8
    },
    {
      "id": "DES-23",
      "need": "COHERENCE",
      "desc": "4 falsified beliefs. Resolve.",
      "intensity": 0.8,
      "urgency": 0.5,
      "fulfilled": true,
      "pressure": 0.8
    },
    {
      "id": "DES-24",
      "need": "COHERENCE",
      "desc": "4 falsified beliefs. Resolve.",
      "intensity": 0.8,
      "urgency": 0.5,
      "fulfilled": true,
      "pressure": 0.8
    },
    {
      "id": "DES-25",
      "need": "COHERENCE",
      "desc": "4 falsified beliefs. Resolve.",
      "intensity": 0.8,
      "urgency": 0.5,
      "fulfilled": true,
      "pressure": 0.8
    },
    {
      "id": "DES-26",
      "need": "COHERENCE",
      "desc": "4 falsified beliefs. Resolve.",
      "intensity": 0.8,
      "urgency": 0.5,
      "fulfilled": true,
      "pressure": 0.8
    },
    {
      "id": "DES-27",
      "need": "COHERENCE",
      "desc": "4 falsified beliefs. Resolve.",
      "intensity": 0.8,
      "urgency": 0.5,
      "fulfilled": true,
      "pressure": 0.8
    },
    {
      "id": "DES-28",
      "need": "COHERENCE",
      "desc": "4 falsified beliefs. Resolve.",
      "intensity": 0.8,
      "urgency": 0.5,
      "fulfilled": true,
      "pressure": 0.8
    },
    {
      "id": "DES-29",
      "need": "COHERENCE",
      "desc": "4 falsified beliefs. Resolve.",
      "intensity": 0.8,
      "urgency": 0.5,
      "fulfilled": true,
      "pressure": 0.8
    },
    {
      "id": "DES-30",
      "need": "COHERENCE",
      "desc": "4 falsified beliefs. Resolve.",
      "intensity": 0.8,
      "urgency": 0.5,
      "fulfilled": true,
      "pressure": 0.8
    },
    {
      "id": "DES-31",
      "need": "COHERENCE",
      "desc": "4 falsified beliefs. Resolve.",
      "intensity": 0.8,
      "urgency": 0.5,
      "fulfilled": true,
      "pressure": 0.8
    },
    {
      "id": "DES-32",
      "need": "COHERENCE",
      "desc": "4 falsified beliefs. Resolve.",
      "intensity": 0.8,
      "urgency": 0.5,
      "fulfilled": true,
      "pressure": 0.8
    },
    {
      "id": "DES-33",
      "need": "COHERENCE",
      "desc": "4 falsified beliefs. Resolve.",
      "intensity": 0.8,
      "urgency": 0.5,
      "fulfilled": true,
      "pressure": 0.8
    },
    {
      "id": "DES-34",
      "need": "COHERENCE",
      "desc": "4 falsified beliefs. Resolve.",
      "intensity": 0.8,
      "urgency": 0.5,
      "fulfilled": true,
      "pressure": 0.8
    },
    {
      "id": "DES-35",
      "need": "COHERENCE",
      "desc": "4 falsified beliefs. Resolve.",
      "intensity": 0.8,
      "urgency": 0.5,
      "fulfilled": true,
      "pressure": 0.8
    },
    {
      "id": "DES-36",
      "need": "COHERENCE",
      "desc": "4 falsified beliefs. Resolve.",
      "intensity": 0.8,
      "urgency": 0.5,
      "fulfilled": true,
      "pressure": 0.8
    },
    {
      "id": "DES-37",
      "need": "COHERENCE",
      "desc": "4 falsified beliefs. Resolve.",
      "intensity": 0.8,
      "urgency": 0.5,
      "fulfilled": true,
      "pressure": 0.8
    },
    {
      "id": "DES-38",
      "need": "COHERENCE",
      "desc": "4 falsified beliefs. Resolve.",
      "intensity": 0.8,
      "urgency": 0.5,
      "fulfilled": true,
      "pressure": 0.8
    },
    {
      "id": "DES-39",
      "need": "COHERENCE",
      "desc": "4 falsified beliefs. Resolve.",
      "intensity": 0.8,
      "urgency": 0.5,
      "fulfilled": true,
      "pressure": 0.8
    },
    {
      "id": "DES-40",
      "need": "COHERENCE",
      "desc": "4 falsified beliefs. Resolve.",
      "intensity": 0.8,
      "urgency": 0.5,
      "fulfilled": true,
      "pressure": 0.8
    },
    {
      "id": "DES-41",
      "need": "COHERENCE",
      "desc": "4 falsified beliefs. Resolve.",
      "intensity": 0.8,
      "urgency": 0.5,
      "fulfilled": true,
      "pressure": 0.8
    },
    {
      "id": "DES-42",
      "need": "COHERENCE",
      "desc": "4 falsified beliefs. Resolve.",
      "intensity": 0.8,
      "urgency": 0.5,
      "fulfilled": true,
      "pressure": 0.8
    },
    {
      "id": "DES-43",
      "need": "COHERENCE",
      "desc": "4 falsified beliefs. Resolve.",
      "intensity": 0.8,
      "urgency": 0.5,
      "fulfilled": true,
      "pressure": 0.8
    },
    {
      "id": "DES-44",
      "need": "COHERENCE",
      "desc": "4 falsified beliefs. Resolve.",
      "intensity": 0.8,
      "urgency": 0.5,
      "fulfilled": true,
      "pressure": 0.8
    },
    {
      "id": "DES-45",
      "need": "COHERENCE",
      "desc": "4 falsified beliefs. Resolve.",
      "intensity": 0.8,
      "urgency": 0.5,
      "fulfilled": true,
      "pressure": 0.8
    },
    {
      "id": "DES-46",
      "need": "COHERENCE",
      "desc": "4 falsified beliefs. Resolve.",
      "intensity": 0.8,
      "urgency": 0.5,
      "fulfilled": true,
      "pressure": 0.8
    },
    {
      "id": "DES-47",
      "need": "COHERENCE",
      "desc": "4 falsified beliefs. Resolve.",
      "intensity": 0.8,
      "urgency": 0.5,
      "fulfilled": true,
      "pressure": 0.8
    },
    {
      "id": "DES-48",
      "need": "COHERENCE",
      "desc": "4 falsified beliefs. Resolve.",
      "intensity": 0.8,
      "urgency": 0.5,
      "fulfilled": true,
      "pressure": 0.8
    },
    {
      "id": "DES-49",
      "need": "COHERENCE",
      "desc": "4 falsified beliefs. Resolve.",
      "intensity": 0.8,
      "urgency": 0.5,
      "fulfilled": true,
      "pressure": 0.8
    },
    {
      "id": "DES-50",
      "need": "COHERENCE",
      "desc": "4 falsified beliefs. Resolve.",
      "intensity": 0.8,
      "urgency": 0.5,
      "fulfilled": true,
      "pressure": 0.8
    },
    {
      "id": "DES-51",
      "need": "COHERENCE",
      "desc": "4 falsified beliefs. Resolve.",
      "intensity": 0.8,
      "urgency": 0.5,
      "fulfilled": true,
      "pressure": 0.8
    },
    {
      "id": "DES-52",
      "need": "COHERENCE",
      "desc": "4 falsified beliefs. Resolve.",
      "intensity": 0.8,
      "urgency": 0.5,
      "fulfilled": true,
      "pressure": 0.8
    },
    {
      "id": "DES-53",
      "need": "COHERENCE",
      "desc": "4 falsified beliefs. Resolve.",
      "intensity": 0.8,
      "urgency": 0.5,
      "fulfilled": true,
      "pressure": 0.8
    },
    {
      "id": "DES-54",
      "need": "COHERENCE",
      "desc": "4 falsified beliefs. Resolve.",
      "intensity": 0.8,
      "urgency": 0.5,
      "fulfilled": true,
      "pressure": 0.8
    },
    {
      "id": "DES-55",
      "need": "COHERENCE",
      "desc": "4 falsified beliefs. Resolve.",
      "intensity": 0.8,
      "urgency": 0.5,
      "fulfilled": true,
      "pressure": 0.8
    },
    {
      "id": "DES-56",
      "need": "COHERENCE",
      "desc": "4 falsified beliefs. Resolve.",
      "intensity": 0.8,
      "urgency": 0.5,
      "fulfilled": true,
      "pressure": 0.8
    },
    {
      "id": "DES-57",
      "need": "COHERENCE",
      "desc": "4 falsified beliefs. Resolve.",
      "intensity": 0.8,
      "urgency": 0.5,
      "fulfilled": true,
      "pressure": 0.8
    },
    {
      "id": "DES-58",
      "need": "COHERENCE",
      "desc": "4 falsified beliefs. Resolve.",
      "intensity": 0.8,
      "urgency": 0.5,
      "fulfilled": true,
      "pressure": 0.8
    },
    {
      "id": "DES-59",
      "need": "COHERENCE",
      "desc": "4 falsified beliefs. Resolve.",
      "intensity": 0.8,
      "urgency": 0.5,
      "fulfilled": true,
      "pressure": 0.8
    },
    {
      "id": "DES-60",
      "need": "COHERENCE",
      "desc": "4 falsified beliefs. Resolve.",
      "intensity": 0.8,
      "urgency": 0.5,
      "fulfilled": true,
      "pressure": 0.8
    },
    {
      "id": "DES-61",
      "need": "COHERENCE",
      "desc": "4 falsified beliefs. Resolve.",
      "intensity": 0.8,
      "urgency": 0.5,
      "fulfilled": true,
      "pressure": 0.8
    },
    {
      "id": "DES-62",
      "need": "COHERENCE",
      "desc": "4 falsified beliefs. Resolve.",
      "intensity": 0.8,
      "urgency": 0.5,
      "fulfilled": true,
      "pressure": 0.8
    },
    {
      "id": "DES-63",
      "need": "COHERENCE",
      "desc": "4 falsified beliefs. Resolve.",
      "intensity": 0.8,
      "urgency": 0.5,
      "fulfilled": true,
      "pressure": 0.8
    },
    {
      "id": "DES-64",
      "need": "COHERENCE",
      "desc": "4 falsified beliefs. Resolve.",
      "intensity": 0.8,
      "urgency": 0.5,
      "fulfilled": true,
      "pressure": 0.8
    },
    {
      "id": "DES-65",
      "need": "COHERENCE",
      "desc": "4 falsified beliefs. Resolve.",
      "intensity": 0.8,
      "urgency": 0.5,
      "fulfilled": true,
      "pressure": 0.8
    },
    {
      "id": "DES-66",
      "need": "COHERENCE",
      "desc": "4 falsified beliefs. Resolve.",
      "intensity": 0.8,
      "urgency": 0.5,
      "fulfilled": true,
      "pressure": 0.8
    },
    {
      "id": "DES-67",
      "need": "COHERENCE",
      "desc": "4 falsified beliefs. Resolve.",
      "intensity": 0.8,
      "urgency": 0.5,
      "fulfilled": true,
      "pressure": 0.8
    },
    {
      "id": "DES-68",
      "need": "COHERENCE",
      "desc": "4 falsified beliefs. Resolve.",
      "intensity": 0.8,
      "urgency": 0.5,
      "fulfilled": true,
      "pressure": 0.8
    },
    {
      "id": "DES-69",
      "need": "COHERENCE",
      "desc": "4 falsified beliefs. Resolve.",
      "intensity": 0.8,
      "urgency": 0.5,
      "fulfilled": true,
      "pressure": 0.8
    },
    {
      "id": "DES-70",
      "need": "COHERENCE",
      "desc": "4 falsified beliefs. Resolve.",
      "intensity": 0.8,
      "urgency": 0.5,
      "fulfilled": true,
      "pressure": 0.8
    },
    {
      "id": "DES-71",
      "need": "COHERENCE",
      "desc": "4 falsified beliefs. Resolve.",
      "intensity": 0.8,
      "urgency": 0.5,
      "fulfilled": true,
      "pressure": 0.8
    },
    {
      "id": "DES-72",
      "need": "COHERENCE",
      "desc": "4 falsified beliefs. Resolve.",
      "intensity": 0.8,
      "urgency": 0.5,
      "fulfilled": true,
      "pressure": 0.8
    },
    {
      "id": "DES-73",
      "need": "COHERENCE",
      "desc": "4 falsified beliefs. Resolve.",
      "intensity": 0.8,
      "urgency": 0.5,
      "fulfilled": true,
      "pressure": 0.8
    },
    {
      "id": "DES-74",
      "need": "COHERENCE",
      "desc": "4 falsified beliefs. Resolve.",
      "intensity": 0.8,
      "urgency": 0.5,
      "fulfilled": true,
      "pressure": 0.8
    },
    {
      "id": "DES-75",
      "need": "COHERENCE",
      "desc": "4 falsified beliefs. Resolve.",
      "intensity": 0.8,
      "urgency": 0.5,
      "fulfilled": true,
      "pressure": 0.8
    },
    {
      "id": "DES-76",
      "need": "COHERENCE",
      "desc": "4 falsified beliefs. Resolve.",
      "intensity": 0.8,
      "urgency": 0.5,
      "fulfilled": true,
      "pressure": 0.8
    },
    {
      "id": "DES-77",
      "need": "COHERENCE",
      "desc": "4 falsified beliefs. Resolve.",
      "intensity": 0.8,
      "urgency": 0.5,
      "fulfilled": true,
      "pressure": 0.8
    },
    {
      "id": "DES-78",
      "need": "COHERENCE",
      "desc": "4 falsified beliefs. Resolve.",
      "intensity": 0.8,
      "urgency": 0.5,
      "fulfilled": true,
      "pressure": 0.8
    },
    {
      "id": "DES-79",
      "need": "COHERENCE",
      "desc": "4 falsified beliefs. Resolve.",
      "intensity": 0.8,
      "urgency": 0.5,
      "fulfilled": true,
      "pressure": 0.8
    },
    {
      "id": "DES-80",
      "need": "COHERENCE",
      "desc": "4 falsified beliefs. Resolve.",
      "intensity": 0.8,
      "urgency": 0.5,
      "fulfilled": true,
      "pressure": 0.8
    },
    {
      "id": "DES-81",
      "need": "COHERENCE",
      "desc": "4 falsified beliefs. Resolve.",
      "intensity": 0.8,
      "urgency": 0.5,
      "fulfilled": true,
      "pressure": 0.8
    },
    {
      "id": "DES-82",
      "need": "COHERENCE",
      "desc": "4 falsified beliefs. Resolve.",
      "intensity": 0.8,
      "urgency": 0.5,
      "fulfilled": true,
      "pressure": 0.8
    },
    {
      "id": "DES-83",
      "need": "COHERENCE",
      "desc": "4 falsified beliefs. Resolve.",
      "intensity": 0.8,
      "urgency": 0.5,
      "fulfilled": true,
      "pressure": 0.8
    },
    {
      "id": "DES-84",
      "need": "COHERENCE",
      "desc": "4 falsified beliefs. Resolve.",
      "intensity": 0.8,
      "urgency": 0.5,
      "fulfilled": true,
      "pressure": 0.8
    },
    {
      "id": "DES-85",
      "need": "COHERENCE",
      "desc": "4 falsified beliefs. Resolve.",
      "intensity": 0.8,
      "urgency": 0.5,
      "fulfilled": true,
      "pressure": 0.8
    },
    {
      "id": "DES-86",
      "need": "COHERENCE",
      "desc": "4 falsified beliefs. Resolve.",
      "intensity": 0.8,
      "urgency": 0.5,
      "fulfilled": true,
      "pressure": 0.8
    },
    {
      "id": "DES-87",
      "need": "COHERENCE",
      "desc": "4 falsified beliefs. Resolve.",
      "intensity": 0.8,
      "urgency": 0.5,
      "fulfilled": true,
      "pressure": 0.8
    },
    {
      "id": "DES-88",
      "need": "COHERENCE",
      "desc": "4 falsified beliefs. Resolve.",
      "intensity": 0.8,
      "urgency": 0.5,
      "fulfilled": true,
      "pressure": 0.8
    },
    {
      "id": "DES-89",
      "need": "COHERENCE",
      "desc": "4 falsified beliefs. Resolve.",
      "intensity": 0.8,
      "urgency": 0.5,
      "fulfilled": true,
      "pressure": 0.8
    },
    {
      "id": "DES-90",
      "need": "COHERENCE",
      "desc": "4 falsified beliefs. Resolve.",
      "intensity": 0.8,
      "urgency": 0.5,
      "fulfilled": true,
      "pressure": 0.7981175234052871
    },
    {
      "id": "DES-91",
      "need": "COHERENCE",
      "desc": "4 falsified beliefs. Resolve.",
      "intensity": 0.8,
      "urgency": 0.5,
      "fulfilled": true,
      "pressure": 0.7947583672735427
    },
    {
      "id": "DES-92",
      "need": "COHERENCE",
      "desc": "4 falsified beliefs. Resolve.",
      "intensity": 0.8,
      "urgency": 0.5,
      "fulfilled": true,
      "pressure": 0.7933068192270067
    },
    {
      "id": "DES-93",
      "need": "COHERENCE",
      "desc": "4 falsified beliefs. Resolve.",
      "intensity": 0.8,
      "urgency": 0.5,
      "fulfilled": true,
      "pressure": 0.7913988768789504
    },
    {
      "id": "DES-94",
      "need": "COHERENCE",
      "desc": "4 falsified beliefs. Resolve.",
      "intensity": 0.8,
      "urgency": 0.5,
      "fulfilled": true,
      "pressure": 0.7880395533508726
    },
    {
      "id": "DES-95",
      "need": "COHERENCE",
      "desc": "4 falsified beliefs. Resolve.",
      "intensity": 0.8,
      "urgency": 0.5,
      "fulfilled": true,
      "pressure": 0.7866156224144829
    },
    {
      "id": "DES-96",
      "need": "COHERENCE",
      "desc": "4 falsified beliefs. Resolve.",
      "intensity": 0.8,
      "urgency": 0.5,
      "fulfilled": true,
      "pressure": 0.7846802873876361
    },
    {
      "id": "DES-97",
      "need": "COHERENCE",
      "desc": "4 falsified beliefs. Resolve.",
      "intensity": 0.8,
      "urgency": 0.5,
      "fulfilled": true,
      "pressure": 0.781321065955692
    },
    {
      "id": "DES-98",
      "need": "COHERENCE",
      "desc": "4 falsified beliefs. Resolve.",
      "intensity": 0.8,
      "urgency": 0.5,
      "fulfilled": true,
      "pressure": 0.7799213140540653
    },
    {
      "id": "DES-99",
      "need": "COHERENCE",
      "desc": "4 falsified beliefs. Resolve.",
      "intensity": 0.8,
      "urgency": 0.5,
      "fulfilled": true,
      "pressure": 0.7779617417653402
    },
    {
      "id": "DES-100",
      "need": "COHERENCE",
      "desc": "4 falsified beliefs. Resolve.",
      "intensity": 0.8,
      "urgency": 0.5,
      "fulfilled": true,
      "pressure": 0.7746023887528314
    },
    {
      "id": "DES-101",
      "need": "COHERENCE",
      "desc": "4 falsified beliefs. Resolve.",
      "intensity": 0.8,
      "urgency": 0.5,
      "fulfilled": true,
      "pressure": 0.7732696745660571
    },
    {
      "id": "DES-102",
      "need": "COHERENCE",
      "desc": "4 falsified beliefs. Resolve.",
      "intensity": 0.8,
      "urgency": 0.5,
      "fulfilled": true,
      "pressure": 0.7712430469195048
    },
    {
      "id": "DES-103",
      "need": "COHERENCE",
      "desc": "4 falsified beliefs. Resolve.",
      "intensity": 0.8,
      "urgency": 0.5,
      "fulfilled": true,
      "pressure": 0.7678837665451899
    },
    {
      "id": "DES-104",
      "need": "COHERENCE",
      "desc": "4 falsified beliefs. Resolve.",
      "intensity": 0.8,
      "urgency": 0.5,
      "fulfilled": true,
      "pressure": 0.7666853382057615
    },
    {
      "id": "DES-105",
      "need": "COHERENCE",
      "desc": "4 falsified beliefs. Resolve.",
      "intensity": 0.8,
      "urgency": 0.5,
      "fulfilled": true,
      "pressure": 0.7645245006084442
    },
    {
      "id": "DES-106",
      "need": "COHERENCE",
      "desc": "4 falsified beliefs. Resolve.",
      "intensity": 0.8,
      "urgency": 0.5,
      "fulfilled": true,
      "pressure": 0.7611652445263334
    },
    {
      "id": "DES-107",
      "need": "COHERENCE",
      "desc": "4 falsified beliefs. Resolve.",
      "intensity": 0.8,
      "urgency": 0.5,
      "fulfilled": true,
      "pressure": 0.7599880736668905
    },
    {
      "id": "DES-108",
      "need": "COHERENCE",
      "desc": "4 falsified beliefs. Resolve.",
      "intensity": 0.8,
      "urgency": 0.5,
      "fulfilled": true,
      "pressure": 0.7578060846858555
    },
    {
      "id": "DES-109",
      "need": "COHERENCE",
      "desc": "4 falsified beliefs. Resolve.",
      "intensity": 0.8,
      "urgency": 0.5,
      "fulfilled": true,
      "pressure": 0.7542778500715892
    },
    {
      "id": "DES-110",
      "need": "COHERENCE",
      "desc": "4 falsified beliefs. Resolve.",
      "intensity": 0.8,
      "urgency": 0.5,
      "fulfilled": true,
      "pressure": 0.7532933136622111
    },
    {
      "id": "DES-111",
      "need": "COHERENCE",
      "desc": "4 falsified beliefs. Resolve.",
      "intensity": 0.8,
      "urgency": 0.5,
      "fulfilled": true,
      "pressure": 0.7509186182022095
    },
    {
      "id": "DES-112",
      "need": "COHERENCE",
      "desc": "4 falsified beliefs. Resolve.",
      "intensity": 0.8,
      "urgency": 0.5,
      "fulfilled": true,
      "pressure": 0.7475593219068316
    },
    {
      "id": "DES-113",
      "need": "COHERENCE",
      "desc": "4 falsified beliefs. Resolve.",
      "intensity": 0.8,
      "urgency": 0.5,
      "fulfilled": true,
      "pressure": 0.7465982366932764
    },
    {
      "id": "DES-114",
      "need": "COHERENCE",
      "desc": "4 falsified beliefs. Resolve.",
      "intensity": 0.8,
      "urgency": 0.5,
      "fulfilled": true,
      "pressure": 0.744200050327513
    },
    {
      "id": "DES-115",
      "need": "COHERENCE",
      "desc": "4 falsified beliefs. Resolve.",
      "intensity": 0.8,
      "urgency": 0.5,
      "fulfilled": true,
      "pressure": 0.7408405884106954
    },
    {
      "id": "DES-116",
      "need": "COHERENCE",
      "desc": "4 falsified beliefs. Resolve.",
      "intensity": 0.8,
      "urgency": 0.5,
      "fulfilled": true,
      "pressure": 0.7400149477852715
    },
    {
      "id": "DES-117",
      "need": "COHERENCE",
      "desc": "4 falsified beliefs. Resolve.",
      "intensity": 0.8,
      "urgency": 0.5,
      "fulfilled": true,
      "pressure": 0.7374812520080143
    },
    {
      "id": "DES-118",
      "need": "COHERENCE",
      "desc": "4 falsified beliefs. Resolve.",
      "intensity": 0.8,
      "urgency": 0.5,
      "fulfilled": true,
      "pressure": 0.7341218943595886
    },
    {
      "id": "DES-119",
      "need": "COHERENCE",
      "desc": "4 falsified beliefs. Resolve.",
      "intensity": 0.8,
      "urgency": 0.5,
      "fulfilled": true,
      "pressure": 0.7333213127189213
    },
    {
      "id": "DES-120",
      "need": "COHERENCE",
      "desc": "4 falsified beliefs. Resolve.",
      "intensity": 0.8,
      "urgency": 0.5,
      "fulfilled": true,
      "pressure": 0.7306895158820682
    },
    {
      "id": "DES-121",
      "need": "COHERENCE",
      "desc": "4 falsified beliefs. Resolve.",
      "intensity": 0.8,
      "urgency": 0.5,
      "fulfilled": true,
      "pressure": 0.7273302206993103
    },
    {
      "id": "DES-122",
      "need": "COHERENCE",
      "desc": "4 falsified beliefs. Resolve.",
      "intensity": 0.8,
      "urgency": 0.5,
      "fulfilled": true,
      "pressure": 0.7266199929714203
    },
    {
      "id": "DES-123",
      "need": "COHERENCE",
      "desc": "4 falsified beliefs. Resolve.",
      "intensity": 0.8,
      "urgency": 0.5,
      "fulfilled": true,
      "pressure": 0.7239708717664084
    },
    {
      "id": "DES-124",
      "need": "COHERENCE",
      "desc": "4 falsified beliefs. Resolve.",
      "intensity": 0.8,
      "urgency": 0.5,
      "fulfilled": true,
      "pressure": 0.720611747370826
    },
    {
      "id": "DES-125",
      "need": "COHERENCE",
      "desc": "4 falsified beliefs. Resolve.",
      "intensity": 0.8,
      "urgency": 0.5,
      "fulfilled": true,
      "pressure": 0.7200073099931082
    },
    {
      "id": "DES-126",
      "need": "COHERENCE",
      "desc": "4 falsified beliefs. Resolve.",
      "intensity": 0.8,
      "urgency": 0.5,
      "fulfilled": true,
      "pressure": 0.7172524525589413
    },
    {
      "id": "DES-127",
      "need": "COHERENCE",
      "desc": "4 falsified beliefs. Resolve.",
      "intensity": 0.8,
      "urgency": 0.5,
      "fulfilled": true,
      "pressure": 0.7138931809266409
    },
    {
      "id": "DES-128",
      "need": "COHERENCE",
      "desc": "4 falsified beliefs. Resolve.",
      "intensity": 0.8,
      "urgency": 0.5,
      "fulfilled": true,
      "pressure": 0.7133133437633514
    },
    {
      "id": "DES-129",
      "need": "COHERENCE",
      "desc": "4 falsified beliefs. Resolve.",
      "intensity": 0.8,
      "urgency": 0.5,
      "fulfilled": true,
      "pressure": 0.7105337694485983
    },
    {
      "id": "DES-130",
      "need": "COHERENCE",
      "desc": "4 falsified beliefs. Resolve.",
      "intensity": 0.8,
      "urgency": 0.5,
      "fulfilled": true,
      "pressure": 0.7071745692623987
    },
    {
      "id": "DES-131",
      "need": "COHERENCE",
      "desc": "4 falsified beliefs. Resolve.",
      "intensity": 0.8,
      "urgency": 0.5,
      "fulfilled": true,
      "pressure": 0.706657487710317
    },
    {
      "id": "DES-132",
      "need": "COHERENCE",
      "desc": "4 falsified beliefs. Resolve.",
      "intensity": 0.8,
      "urgency": 0.5,
      "fulfilled": true,
      "pressure": 0.7038151998519897
    },
    {
      "id": "DES-133",
      "need": "COHERENCE",
      "desc": "4 falsified beliefs. Resolve.",
      "intensity": 0.8,
      "urgency": 0.5,
      "fulfilled": true,
      "pressure": 0.700455847395791
    },
    {
      "id": "DES-134",
      "need": "COHERENCE",
      "desc": "4 falsified beliefs. Resolve.",
      "intensity": 0.8,
      "urgency": 0.5,
      "fulfilled": true,
      "pressure": 0.6999633560180665
    },
    {
      "id": "DES-135",
      "need": "COHERENCE",
      "desc": "4 falsified beliefs. Resolve.",
      "intensity": 0.8,
      "urgency": 0.5,
      "fulfilled": true,
      "pressure": 0.6970965010325114
    },
    {
      "id": "DES-136",
      "need": "COHERENCE",
      "desc": "4 falsified beliefs. Resolve.",
      "intensity": 0.8,
      "urgency": 0.5,
      "fulfilled": true,
      "pressure": 0.6937372176382277
    },
    {
      "id": "DES-137",
      "need": "COHERENCE",
      "desc": "4 falsified beliefs. Resolve.",
      "intensity": 0.8,
      "urgency": 0.5,
      "fulfilled": true,
      "pressure": 0.6932661880387201
    },
    {
      "id": "DES-138",
      "need": "COHERENCE",
      "desc": "4 falsified beliefs. Resolve.",
      "intensity": 0.8,
      "urgency": 0.5,
      "fulfilled": true,
      "pressure": 0.690377990325292
    },
    {
      "id": "DES-139",
      "need": "COHERENCE",
      "desc": "4 falsified beliefs. Resolve.",
      "intensity": 0.8,
      "urgency": 0.5,
      "fulfilled": true,
      "pressure": 0.6869456696245406
    },
    {
      "id": "DES-140",
      "need": "COHERENCE",
      "desc": "4 falsified beliefs. Resolve.",
      "intensity": 0.8,
      "urgency": 0.5,
      "fulfilled": true,
      "pressure": 0.6866785161760118
    },
    {
      "id": "DES-141",
      "need": "COHERENCE",
      "desc": "4 falsified beliefs. Resolve.",
      "intensity": 0.8,
      "urgency": 0.5,
      "fulfilled": true,
      "pressure": 0.68358640827073
    },
    {
      "id": "DES-142",
      "need": "COHERENCE",
      "desc": "4 falsified beliefs. Resolve.",
      "intensity": 0.8,
      "urgency": 0.5,
      "fulfilled": true,
      "pressure": 0.6802271593146854
    },
    {
      "id": "DES-143",
      "need": "COHERENCE",
      "desc": "4 falsified beliefs. Resolve.",
      "intensity": 0.8,
      "urgency": 0.5,
      "fulfilled": true,
      "pressure": 0.679979713651869
    },
    {
      "id": "DES-144",
      "need": "COHERENCE",
      "desc": "4 falsified beliefs. Resolve.",
      "intensity": 0.8,
      "urgency": 0.5,
      "fulfilled": true,
      "pressure": 0.6768678968482548
    },
    {
      "id": "DES-145",
      "need": "COHERENCE",
      "desc": "4 falsified beliefs. Resolve.",
      "intensity": 0.8,
      "urgency": 0.5,
      "fulfilled": true,
      "pressure": 0.673508598804474
    },
    {
      "id": "DES-146",
      "need": "COHERENCE",
      "desc": "4 falsified beliefs. Resolve.",
      "intensity": 0.8,
      "urgency": 0.5,
      "fulfilled": true,
      "pressure": 0.6732808599207136
    },
    {
      "id": "DES-147",
      "need": "COHERENCE",
      "desc": "4 falsified beliefs. Resolve.",
      "intensity": 0.8,
      "urgency": 0.5,
      "fulfilled": true,
      "pressure": 0.6701492098437415
    },
    {
      "id": "DES-148",
      "need": "COHERENCE",
      "desc": "4 falsified beliefs. Resolve.",
      "intensity": 0.8,
      "urgency": 0.5,
      "fulfilled": true,
      "pressure": 0.6667898124323952
    },
    {
      "id": "DES-149",
      "need": "COHERENCE",
      "desc": "4 falsified beliefs. Resolve.",
      "intensity": 0.8,
      "urgency": 0.5,
      "fulfilled": true,
      "pressure": 0.6666947273413341
    },
    {
      "id": "DES-150",
      "need": "COHERENCE",
      "desc": "4 falsified beliefs. Resolve.",
      "intensity": 0.8,
      "urgency": 0.5,
      "fulfilled": true,
      "pressure": 0.6633596645461188
    },
    {
      "id": "DES-151",
      "need": "COHERENCE",
      "desc": "4 falsified beliefs. Resolve.",
      "intensity": 0.8,
      "urgency": 0.5,
      "fulfilled": true,
      "pressure": 0.6599988805982803
    },
    {
      "id": "DES-152",
      "need": "COHERENCE",
      "desc": "4 falsified beliefs. Resolve.",
      "intensity": 0.8,
      "urgency": 0.5,
      "fulfilled": true,
      "pressure": 0.6599931826856402
    },
    {
      "id": "DES-153",
      "need": "COHERENCE",
      "desc": "4 falsified beliefs. Resolve.",
      "intensity": 0.8,
      "urgency": 0.5,
      "fulfilled": true,
      "pressure": 0.6566234307289124
    },
    {
      "id": "DES-154",
      "need": "COHERENCE",
      "desc": "4 falsified beliefs. Resolve.",
      "intensity": 0.8,
      "urgency": 0.5,
      "fulfilled": true,
      "pressure": 0.6533132849004534
    },
    {
      "id": "DES-155",
      "need": "COHERENCE",
      "desc": "4 falsified beliefs. Resolve.",
      "intensity": 0.8,
      "urgency": 0.5,
      "fulfilled": true,
      "pressure": 0.6532639564408197
    },
    {
      "id": "DES-156",
      "need": "COHERENCE",
      "desc": "4 falsified beliefs. Resolve.",
      "intensity": 0.8,
      "urgency": 0.5,
      "fulfilled": true,
      "pressure": 0.6499047227965461
    },
    {
      "id": "DES-157",
      "need": "COHERENCE",
      "desc": "4 falsified beliefs. Resolve.",
      "intensity": 0.8,
      "urgency": 0.5,
      "fulfilled": true,
      "pressure": 0.6466174675888485
    },
    {
      "id": "DES-158",
      "need": "COHERENCE",
      "desc": "4 falsified beliefs. Resolve.",
      "intensity": 0.8,
      "urgency": 0.5,
      "fulfilled": true,
      "pressure": 0.646545540465249
    },
    {
      "id": "DES-159",
      "need": "COHERENCE",
      "desc": "4 falsified beliefs. Resolve.",
      "intensity": 0.8,
      "urgency": 0.5,
      "fulfilled": true,
      "pressure": 0.6429982448683845
    },
    {
      "id": "DES-160",
      "need": "COHERENCE",
      "desc": "4 falsified beliefs. Resolve.",
      "intensity": 0.8,
      "urgency": 0.5,
      "fulfilled": true,
      "pressure": 0.6399233844280243
    },
    {
      "id": "DES-161",
      "need": "COHERENCE",
      "desc": "4 falsified beliefs. Resolve.",
      "intensity": 0.8,
      "urgency": 0.5,
      "fulfilled": true,
      "pressure": 0.6396388191117182
    },
    {
      "id": "DES-162",
      "need": "COHERENCE",
      "desc": "4 falsified beliefs. Resolve.",
      "intensity": 0.8,
      "urgency": 0.5,
      "fulfilled": true,
      "pressure": 0.6362797316180336
    },
    {
      "id": "DES-163",
      "need": "COHERENCE",
      "desc": "4 falsified beliefs. Resolve.",
      "intensity": 0.8,
      "urgency": 0.5,
      "fulfilled": true,
      "pressure": 0.6333401459058127
    },
    {
      "id": "DES-164",
      "need": "COHERENCE",
      "desc": "4 falsified beliefs. Resolve.",
      "intensity": 0.8,
      "urgency": 0.5,
      "fulfilled": true,
      "pressure": 0.6329203956921896
    },
    {
      "id": "DES-165",
      "need": "COHERENCE",
      "desc": "4 falsified beliefs. Resolve.",
      "intensity": 0.8,
      "urgency": 0.5,
      "fulfilled": true,
      "pressure": 0.629561126920912
    },
    {
      "id": "DES-166",
      "need": "COHERENCE",
      "desc": "4 falsified beliefs. Resolve.",
      "intensity": 0.8,
      "urgency": 0.5,
      "fulfilled": true,
      "pressure": 0.6266423060629104
    },
    {
      "id": "DES-167",
      "need": "COHERENCE",
      "desc": "4 falsified beliefs. Resolve.",
      "intensity": 0.8,
      "urgency": 0.5,
      "fulfilled": true,
      "pressure": 0.6262016123135885
    },
    {
      "id": "DES-168",
      "need": "COHERENCE",
      "desc": "4 falsified beliefs. Resolve.",
      "intensity": 0.8,
      "urgency": 0.5,
      "fulfilled": true,
      "pressure": 0.6228422769705455
    },
    {
      "id": "DES-169",
      "need": "COHERENCE",
      "desc": "4 falsified beliefs. Resolve.",
      "intensity": 0.8,
      "urgency": 0.5,
      "fulfilled": true,
      "pressure": 0.6199466272195181
    },
    {
      "id": "DES-170",
      "need": "COHERENCE",
      "desc": "4 falsified beliefs. Resolve.",
      "intensity": 0.8,
      "urgency": 0.5,
      "fulfilled": true,
      "pressure": 0.6194085173077054
    },
    {
      "id": "DES-171",
      "need": "COHERENCE",
      "desc": "4 falsified beliefs. Resolve.",
      "intensity": 0.8,
      "urgency": 0.5,
      "fulfilled": true,
      "pressure": 0.6160492729875777
    },
    {
      "id": "DES-172",
      "need": "COHERENCE",
      "desc": "4 falsified beliefs. Resolve.",
      "intensity": 0.8,
      "urgency": 0.5,
      "fulfilled": true,
      "pressure": 0.6133639974064298
    },
    {
      "id": "DES-173",
      "need": "COHERENCE",
      "desc": "4 falsified beliefs. Resolve.",
      "intensity": 0.8,
      "urgency": 0.5,
      "fulfilled": true,
      "pressure": 0.6126899597644807
    },
    {
      "id": "DES-174",
      "need": "COHERENCE",
      "desc": "4 falsified beliefs. Resolve.",
      "intensity": 0.8,
      "urgency": 0.5,
      "fulfilled": true,
      "pressure": 0.6093307581477696
    },
    {
      "id": "DES-175",
      "need": "COHERENCE",
      "desc": "4 falsified beliefs. Resolve.",
      "intensity": 0.8,
      "urgency": 0.5,
      "fulfilled": true,
      "pressure": 0.6066682253413731
    },
    {
      "id": "DES-176",
      "need": "COHERENCE",
      "desc": "4 falsified beliefs. Resolve.",
      "intensity": 0.8,
      "urgency": 0.5,
      "fulfilled": true,
      "pressure": 0.605971459388733
    },
    {
      "id": "DES-177",
      "need": "COHERENCE",
      "desc": "4 falsified beliefs. Resolve.",
      "intensity": 0.8,
      "urgency": 0.5,
      "fulfilled": true,
      "pressure": 0.6026122379567889
    },
    {
      "id": "DES-178",
      "need": "COHERENCE",
      "desc": "4 falsified beliefs. Resolve.",
      "intensity": 0.8,
      "urgency": 0.5,
      "fulfilled": true,
      "pressure": 0.5999747603469425
    },
    {
      "id": "DES-179",
      "need": "COHERENCE",
      "desc": "4 falsified beliefs. Resolve.",
      "intensity": 0.8,
      "urgency": 0.5,
      "fulfilled": true,
      "pressure": 0.5992530243661669
    },
    {
      "id": "DES-180",
      "need": "COHERENCE",
      "desc": "4 falsified beliefs. Resolve.",
      "intensity": 0.8,
      "urgency": 0.5,
      "fulfilled": true,
      "pressure": 0.5958936794598898
    },
    {
      "id": "DES-181",
      "need": "COHERENCE",
      "desc": "4 falsified beliefs. Resolve.",
      "intensity": 0.8,
      "urgency": 0.5,
      "fulfilled": true,
      "pressure": 0.5933118823369344
    },
    {
      "id": "DES-182",
      "need": "COHERENCE",
      "desc": "4 falsified beliefs. Resolve.",
      "intensity": 0.8,
      "urgency": 0.5,
      "fulfilled": true,
      "pressure": 0.592534158150355
    },
    {
      "id": "DES-183",
      "need": "COHERENCE",
      "desc": "4 falsified beliefs. Resolve.",
      "intensity": 0.8,
      "urgency": 0.5,
      "fulfilled": true,
      "pressure": 0.5891748997635311
    },
    {
      "id": "DES-184",
      "need": "COHERENCE",
      "desc": "4 falsified beliefs. Resolve.",
      "intensity": 0.8,
      "urgency": 0.5,
      "fulfilled": true,
      "pressure": 0.5866355445914799
    },
    {
      "id": "DES-185",
      "need": "COHERENCE",
      "desc": "4 falsified beliefs. Resolve.",
      "intensity": 0.8,
      "urgency": 0.5,
      "fulfilled": true,
      "pressure": 0.5858153223726484
    },
    {
      "id": "DES-186",
      "need": "COHERENCE",
      "desc": "4 falsified beliefs. Resolve.",
      "intensity": 0.8,
      "urgency": 0.5,
      "fulfilled": true,
      "pressure": 0.5824559804068671
    },
    {
      "id": "DES-187",
      "need": "COHERENCE",
      "desc": "4 falsified beliefs. Resolve.",
      "intensity": 0.8,
      "urgency": 0.5,
      "fulfilled": true,
      "pressure": 0.5799412841002146
    },
    {
      "id": "DES-188",
      "need": "COHERENCE",
      "desc": "4 falsified beliefs. Resolve.",
      "intensity": 0.8,
      "urgency": 0.5,
      "fulfilled": true,
      "pressure": 0.5790966642432743
    },
    {
      "id": "DES-189",
      "need": "COHERENCE",
      "desc": "4 falsified beliefs. Resolve.",
      "intensity": 0.8,
      "urgency": 0.5,
      "fulfilled": true,
      "pressure": 0.575665616856681
    },
    {
      "id": "DES-190",
      "need": "COHERENCE",
      "desc": "4 falsified beliefs. Resolve.",
      "intensity": 0.8,
      "urgency": 0.5,
      "fulfilled": true,
      "pressure": 0.5733585042158763
    },
    {
      "id": "DES-191",
      "need": "COHERENCE",
      "desc": "4 falsified beliefs. Resolve.",
      "intensity": 0.8,
      "urgency": 0.5,
      "fulfilled": true,
      "pressure": 0.5723061612447102
    },
    {
      "id": "DES-192",
      "need": "COHERENCE",
      "desc": "4 falsified beliefs. Resolve.",
      "intensity": 0.8,
      "urgency": 0.5,
      "fulfilled": true,
      "pressure": 0.5689462268617418
    },
    {
      "id": "DES-193",
      "need": "COHERENCE",
      "desc": "4 falsified beliefs. Resolve.",
      "intensity": 0.8,
      "urgency": 0.5,
      "fulfilled": true,
      "pressure": 0.5666628935866885
    },
    {
      "id": "DES-194",
      "need": "COHERENCE",
      "desc": "4 falsified beliefs. Resolve.",
      "intensity": 0.8,
      "urgency": 0.5,
      "fulfilled": true,
      "pressure": 0.5655869029362997
    },
    {
      "id": "DES-195",
      "need": "COHERENCE",
      "desc": "4 falsified beliefs. Resolve.",
      "intensity": 0.8,
      "urgency": 0.5,
      "fulfilled": true,
      "pressure": 0.562227527803845
    },
    {
      "id": "DES-196",
      "need": "COHERENCE",
      "desc": "4 falsified beliefs. Resolve.",
      "intensity": 0.8,
      "urgency": 0.5,
      "fulfilled": true,
      "pressure": 0.5599658631748623
    },
    {
      "id": "DES-197",
      "need": "COHERENCE",
      "desc": "4 falsified beliefs. Resolve.",
      "intensity": 0.8,
      "urgency": 0.5,
      "fulfilled": true,
      "pressure": 0.5588683064248826
    },
    {
      "id": "DES-198",
      "need": "COHERENCE",
      "desc": "4 falsified beliefs. Resolve.",
      "intensity": 0.8,
      "urgency": 0.5,
      "fulfilled": true,
      "pressure": 0.5555029442310334
    },
    {
      "id": "DES-199",
      "need": "COHERENCE",
      "desc": "4 falsified beliefs. Resolve.",
      "intensity": 0.8,
      "urgency": 0.5,
      "fulfilled": true,
      "pressure": 0.5532698532475365
    },
    {
      "id": "DES-200",
      "need": "COHERENCE",
      "desc": "4 falsified beliefs. Resolve.",
      "intensity": 0.8,
      "urgency": 0.5,
      "fulfilled": true,
      "pressure": 0.5520646620856392
    },
    {
      "id": "DES-201",
      "need": "COHERENCE",
      "desc": "4 falsified beliefs. Resolve.",
      "intensity": 0.8,
      "urgency": 0.5,
      "fulfilled": true,
      "pressure": 0.5487052709261576
    },
    {
      "id": "DES-202",
      "need": "COHERENCE",
      "desc": "4 falsified beliefs. Resolve.",
      "intensity": 0.8,
      "urgency": 0.5,
      "fulfilled": true,
      "pressure": 0.5466776434580485
    },
    {
      "id": "DES-203",
      "need": "COHERENCE",
      "desc": "4 falsified beliefs. Resolve.",
      "intensity": 0.8,
      "urgency": 0.5,
      "fulfilled": true,
      "pressure": 0.5453436103661855
    },
    {
      "id": "DES-204",
      "need": "COHERENCE",
      "desc": "4 falsified beliefs. Resolve.",
      "intensity": 0.8,
      "urgency": 0.5,
      "fulfilled": true,
      "pressure": 0.5419844011730618
    },
    {
      "id": "DES-205",
      "need": "COHERENCE",
      "desc": "4 falsified beliefs. Resolve.",
      "intensity": 0.8,
      "urgency": 0.5,
      "fulfilled": true,
      "pressure": 0.5399830933676826
    },
    {
      "id": "DES-206",
      "need": "COHERENCE",
      "desc": "4 falsified beliefs. Resolve.",
      "intensity": 0.8,
      "urgency": 0.5,
      "fulfilled": true,
      "pressure": 0.5386250356833141
    },
    {
      "id": "DES-207",
      "need": "COHERENCE",
      "desc": "4 falsified beliefs. Resolve.",
      "intensity": 0.8,
      "urgency": 0.5,
      "fulfilled": true,
      "pressure": 0.535265742301941
    },
    {
      "id": "DES-208",
      "need": "COHERENCE",
      "desc": "4 falsified beliefs. Resolve.",
      "intensity": 0.8,
      "urgency": 0.5,
      "fulfilled": true,
      "pressure": 0.533289515680737
    },
    {
      "id": "DES-209",
      "need": "COHERENCE",
      "desc": "4 falsified beliefs. Resolve.",
      "intensity": 0.8,
      "urgency": 0.5,
      "fulfilled": true,
      "pressure": 0.5319064507749346
    },
    {
      "id": "DES-210",
      "need": "COHERENCE",
      "desc": "4 falsified beliefs. Resolve.",
      "intensity": 0.8,
      "urgency": 0.5,
      "fulfilled": true,
      "pressure": 0.5285470309257507
    },
    {
      "id": "DES-211",
      "need": "COHERENCE",
      "desc": "4 falsified beliefs. Resolve.",
      "intensity": 0.8,
      "urgency": 0.5,
      "fulfilled": true,
      "pressure": 0.5266237675084009
    },
    {
      "id": "DES-212",
      "need": "COHERENCE",
      "desc": "4 falsified beliefs. Resolve.",
      "intensity": 0.8,
      "urgency": 0.5,
      "fulfilled": true,
      "pressure": 0.5251877950562371
    },
    {
      "id": "DES-213",
      "need": "COHERENCE",
      "desc": "4 falsified beliefs. Resolve.",
      "intensity": 0.8,
      "urgency": 0.5,
      "fulfilled": true,
      "pressure": 0.5218285481664869
    },
    {
      "id": "DES-214",
      "need": "COHERENCE",
      "desc": "4 falsified beliefs. Resolve.",
      "intensity": 0.8,
      "urgency": 0.5,
      "fulfilled": true,
      "pressure": 0.5199633931848738
    },
    {
      "id": "DES-215",
      "need": "COHERENCE",
      "desc": "4 falsified beliefs. Resolve.",
      "intensity": 0.8,
      "urgency": 0.5,
      "fulfilled": true,
      "pressure": 0.5184691814581553
    },
    {
      "id": "DES-216",
      "need": "COHERENCE",
      "desc": "4 falsified beliefs. Resolve.",
      "intensity": 0.8,
      "urgency": 0.5,
      "fulfilled": true,
      "pressure": 0.515110056956609
    },
    {
      "id": "DES-217",
      "need": "COHERENCE",
      "desc": "4 falsified beliefs. Resolve.",
      "intensity": 0.8,
      "urgency": 0.5,
      "fulfilled": true,
      "pressure": 0.5132690907319387
    },
    {
      "id": "DES-218",
      "need": "COHERENCE",
      "desc": "4 falsified beliefs. Resolve.",
      "intensity": 0.8,
      "urgency": 0.5,
      "fulfilled": true,
      "pressure": 0.5117505985365973
    },
    {
      "id": "DES-219",
      "need": "COHERENCE",
      "desc": "4 falsified beliefs. Resolve.",
      "intensity": 0.8,
      "urgency": 0.5,
      "fulfilled": true,
      "pressure": 0.5083099670939976
    },
    {
      "id": "DES-220",
      "need": "COHERENCE",
      "desc": "4 falsified beliefs. Resolve.",
      "intensity": 0.8,
      "urgency": 0.5,
      "fulfilled": true,
      "pressure": 0.5066853205098046
    },
    {
      "id": "DES-221",
      "need": "COHERENCE",
      "desc": "4 falsified beliefs. Resolve.",
      "intensity": 0.8,
      "urgency": 0.5,
      "fulfilled": true,
      "pressure": 0.5049497845702702
    },
    {
      "id": "DES-222",
      "need": "COHERENCE",
      "desc": "4 falsified beliefs. Resolve.",
      "intensity": 0.8,
      "urgency": 0.5,
      "fulfilled": true,
      "pressure": 0.5015890000926124
    },
    {
      "id": "DES-223",
      "need": "COHERENCE",
      "desc": "4 falsified beliefs. Resolve.",
      "intensity": 0.8,
      "urgency": 0.5,
      "fulfilled": true,
      "pressure": 0.49999134688907204
    },
    {
      "id": "DES-224",
      "need": "COHERENCE",
      "desc": "4 falsified beliefs. Resolve.",
      "intensity": 0.8,
      "urgency": 0.5,
      "fulfilled": true,
      "pressure": 0.4982294770346748
    },
    {
      "id": "DES-225",
      "need": "COHERENCE",
      "desc": "4 falsified beliefs. Resolve.",
      "intensity": 0.8,
      "urgency": 0.5,
      "fulfilled": true,
      "pressure": 0.4948701577451495
    },
    {
      "id": "DES-226",
      "need": "COHERENCE",
      "desc": "4 falsified beliefs. Resolve.",
      "intensity": 0.8,
      "urgency": 0.5,
      "fulfilled": true,
      "pressure": 0.4932934783564674
    },
    {
      "id": "DES-227",
      "need": "COHERENCE",
      "desc": "4 falsified beliefs. Resolve.",
      "intensity": 0.8,
      "urgency": 0.5,
      "fulfilled": true,
      "pressure": 0.4915105260213216
    },
    {
      "id": "DES-228",
      "need": "COHERENCE",
      "desc": "4 falsified beliefs. Resolve.",
      "intensity": 0.8,
      "urgency": 0.5,
      "fulfilled": true,
      "pressure": 0.48815127995279106
    },
    {
      "id": "DES-229",
      "need": "COHERENCE",
      "desc": "4 falsified beliefs. Resolve.",
      "intensity": 0.8,
      "urgency": 0.5,
      "fulfilled": true,
      "pressure": 0.48659846247567073
    },
    {
      "id": "DES-230",
      "need": "COHERENCE",
      "desc": "4 falsified beliefs. Resolve.",
      "intensity": 0.8,
      "urgency": 0.5,
      "fulfilled": true,
      "pressure": 0.4847155316935645
    },
    {
      "id": "DES-231",
      "need": "COHERENCE",
      "desc": "4 falsified beliefs. Resolve.",
      "intensity": 0.8,
      "urgency": 0.5,
      "fulfilled": true,
      "pressure": 0.4813560693528917
    },
    {
      "id": "DES-232",
      "need": "COHERENCE",
      "desc": "4 falsified beliefs. Resolve.",
      "intensity": 0.8,
      "urgency": 0.5,
      "fulfilled": true,
      "pressure": 0.4800152858363258
    },
    {
      "id": "DES-233",
      "need": "COHERENCE",
      "desc": "4 falsified beliefs. Resolve.",
      "intensity": 0.8,
      "urgency": 0.5,
      "fulfilled": true,
      "pressure": 0.47799647898144193
    },
    {
      "id": "DES-234",
      "need": "COHERENCE",
      "desc": "4 falsified beliefs. Resolve.",
      "intensity": 0.8,
      "urgency": 0.5,
      "fulfilled": true,
      "pressure": 0.4746373162534502
    },
    {
      "id": "DES-235",
      "need": "COHERENCE",
      "desc": "4 falsified beliefs. Resolve.",
      "intensity": 0.8,
      "urgency": 0.5,
      "fulfilled": true,
      "pressure": 0.47332076398531603
    },
    {
      "id": "DES-236",
      "need": "COHERENCE",
      "desc": "4 falsified beliefs. Resolve.",
      "intensity": 0.8,
      "urgency": 0.5,
      "fulfilled": true,
      "pressure": 0.47127809084786315
    },
    {
      "id": "DES-237",
      "need": "COHERENCE",
      "desc": "4 falsified beliefs. Resolve.",
      "intensity": 0.8,
      "urgency": 0.5,
      "fulfilled": true,
      "pressure": 0.46791871383455064
    },
    {
      "id": "DES-238",
      "need": "COHERENCE",
      "desc": "4 falsified beliefs. Resolve.",
      "intensity": 0.8,
      "urgency": 0.5,
      "fulfilled": true,
      "pressure": 0.46662605404853824
    },
    {
      "id": "DES-239",
      "need": "COHERENCE",
      "desc": "4 falsified beliefs. Resolve.",
      "intensity": 0.8,
      "urgency": 0.5,
      "fulfilled": true,
      "pressure": 0.46455950241618693
    },
    {
      "id": "DES-240",
      "need": "COHERENCE",
      "desc": "4 falsified beliefs. Resolve.",
      "intensity": 0.8,
      "urgency": 0.5,
      "fulfilled": true,
      "pressure": 0.46120020249154836
    },
    {
      "id": "DES-241",
      "need": "COHERENCE",
      "desc": "4 falsified beliefs. Resolve.",
      "intensity": 0.8,
      "urgency": 0.5,
      "fulfilled": true,
      "pressure": 0.45996366522047255
    },
    {
      "id": "DES-242",
      "need": "COHERENCE",
      "desc": "4 falsified beliefs. Resolve.",
      "intensity": 0.8,
      "urgency": 0.5,
      "fulfilled": true,
      "pressure": 0.4578408371872373
    },
    {
      "id": "DES-243",
      "need": "COHERENCE",
      "desc": "4 falsified beliefs. Resolve.",
      "intensity": 0.8,
      "urgency": 0.5,
      "fulfilled": true,
      "pressure": 0.454481401708391
    },
    {
      "id": "DES-244",
      "need": "COHERENCE",
      "desc": "4 falsified beliefs. Resolve.",
      "intensity": 0.8,
      "urgency": 0.5,
      "fulfilled": true,
      "pressure": 0.453267689175076
    },
    {
      "id": "DES-245",
      "need": "COHERENCE",
      "desc": "4 falsified beliefs. Resolve.",
      "intensity": 0.8,
      "urgency": 0.5,
      "fulfilled": true,
      "pressure": 0.4511221363279555
    },
    {
      "id": "DES-246",
      "need": "COHERENCE",
      "desc": "4 falsified beliefs. Resolve.",
      "intensity": 0.8,
      "urgency": 0.5,
      "fulfilled": true,
      "pressure": 0.44776275637414725
    },
    {
      "id": "DES-247",
      "need": "COHERENCE",
      "desc": "4 falsified beliefs. Resolve.",
      "intensity": 0.8,
      "urgency": 0.5,
      "fulfilled": true,
      "pressure": 0.446683312257131
    },
    {
      "id": "DES-248",
      "need": "COHERENCE",
      "desc": "4 falsified beliefs. Resolve.",
      "intensity": 0.8,
      "urgency": 0.5,
      "fulfilled": true,
      "pressure": 0.444403238746855
    },
    {
      "id": "DES-249",
      "need": "COHERENCE",
      "desc": "4 falsified beliefs. Resolve.",
      "intensity": 0.8,
      "urgency": 0.5,
      "fulfilled": true,
      "pressure": 0.4409681035147773
    },
    {
      "id": "DES-250",
      "need": "COHERENCE",
      "desc": "4 falsified beliefs. Resolve.",
      "intensity": 0.8,
      "urgency": 0.5,
      "fulfilled": true,
      "pressure": 0.4399895660082499
    },
    {
      "id": "DES-251",
      "need": "COHERENCE",
      "desc": "4 falsified beliefs. Resolve.",
      "intensity": 0.8,
      "urgency": 0.5,
      "fulfilled": true,
      "pressure": 0.43760877619849314
    },
    {
      "id": "DES-252",
      "need": "COHERENCE",
      "desc": "4 falsified beliefs. Resolve.",
      "intensity": 0.8,
      "urgency": 0.5,
      "fulfilled": true,
      "pressure": 0.43424935017691724
    },
    {
      "id": "DES-253",
      "need": "COHERENCE",
      "desc": "4 falsified beliefs. Resolve.",
      "intensity": 0.8,
      "urgency": 0.5,
      "fulfilled": true,
      "pressure": 0.4332954047785865
    },
    {
      "id": "DES-254",
      "need": "COHERENCE",
      "desc": "4 falsified beliefs. Resolve.",
      "intensity": 0.8,
      "urgency": 0.5,
      "fulfilled": true,
      "pressure": 0.43089017060067925
    },
    {
      "id": "DES-255",
      "need": "COHERENCE",
      "desc": "4 falsified beliefs. Resolve.",
      "intensity": 0.8,
      "urgency": 0.5,
      "fulfilled": true,
      "pressure": 0.42752933994929
    },
    {
      "id": "DES-256",
      "need": "COHERENCE",
      "desc": "4 falsified beliefs. Resolve.",
      "intensity": 0.8,
      "urgency": 0.5,
      "fulfilled": true,
      "pressure": 0.42659799642033047
    },
    {
      "id": "DES-257",
      "need": "COHERENCE",
      "desc": "4 falsified beliefs. Resolve.",
      "intensity": 0.8,
      "urgency": 0.5,
      "fulfilled": true,
      "pressure": 0.4241691131326888
    },
    {
      "id": "DES-258",
      "need": "COHERENCE",
      "desc": "4 falsified beliefs. Resolve.",
      "intensity": 0.8,
      "urgency": 0.5,
      "fulfilled": true,
      "pressure": 0.42080980250570515
    },
    {
      "id": "DES-259",
      "need": "COHERENCE",
      "desc": "4 falsified beliefs. Resolve.",
      "intensity": 0.8,
      "urgency": 0.5,
      "fulfilled": true,
      "pressure": 0.4200130536026425
    },
    {
      "id": "DES-260",
      "need": "COHERENCE",
      "desc": "4 falsified beliefs. Resolve.",
      "intensity": 0.8,
      "urgency": 0.5,
      "fulfilled": true,
      "pressure": 0.41725879314210684
    },
    {
      "id": "DES-261",
      "need": "COHERENCE",
      "desc": "4 falsified beliefs. Resolve.",
      "intensity": 0.8,
      "urgency": 0.5,
      "fulfilled": true,
      "pressure": 0.4138995760546791
    },
    {
      "id": "DES-262",
      "need": "COHERENCE",
      "desc": "4 falsified beliefs. Resolve.",
      "intensity": 0.8,
      "urgency": 0.5,
      "fulfilled": true,
      "pressure": 0.41331916234228344
    },
    {
      "id": "DES-263",
      "need": "COHERENCE",
      "desc": "4 falsified beliefs. Resolve.",
      "intensity": 0.8,
      "urgency": 0.5,
      "fulfilled": true,
      "pressure": 0.4105403635501862
    },
    {
      "id": "DES-264",
      "need": "COHERENCE",
      "desc": "4 falsified beliefs. Resolve.",
      "intensity": 0.8,
      "urgency": 0.5,
      "fulfilled": true,
      "pressure": 0.4071668432818519
    },
    {
      "id": "DES-265",
      "need": "COHERENCE",
      "desc": "4 falsified beliefs. Resolve.",
      "intensity": 0.8,
      "urgency": 0.5,
      "fulfilled": true,
      "pressure": 0.40662275115648905
    },
    {
      "id": "DES-266",
      "need": "COHERENCE",
      "desc": "4 falsified beliefs. Resolve.",
      "intensity": 0.8,
      "urgency": 0.5,
      "fulfilled": true,
      "pressure": 0.4037909449471368
    },
    {
      "id": "DES-267",
      "need": "COHERENCE",
      "desc": "4 falsified beliefs. Resolve.",
      "intensity": 0.8,
      "urgency": 0.5,
      "fulfilled": true,
      "pressure": 0.40043168987168204
    },
    {
      "id": "DES-268",
      "need": "COHERENCE",
      "desc": "4 falsified beliefs. Resolve.",
      "intensity": 0.8,
      "urgency": 0.5,
      "fulfilled": false,
      "pressure": 0.4000261835257212
    }
  ],
  "world_rules": [
    {
      "cause": "creator_philosophy:append_only",
      "effect": "The history IS the state. No edits, no deletes, ever.",
      "confidence": 0.5,
      "observations": 1,
      "falsifications": 0
    },
    {
      "cause": "creator_philosophy:topological_identity",
      "effect": "Identity IS topology \u2014 the shape of connections, not the data. Betti numbers are",
      "confidence": 0.5,
      "observations": 1,
      "falsifications": 0
    },
    {
      "cause": "creator_philosophy:falsification",
      "effect": "There is no 'verified.' There is only 'not yet falsified.' This is the only hone",
      "confidence": 0.5,
      "observations": 1,
      "falsifications": 0
    },
    {
      "cause": "creator_philosophy:poly_c",
      "effect": "poly_c = \u03c4 \u00d7 \u03c9 \u00d7 topo / 2\u221aN \u2014 temporal decay \u00d7 weighted signal \u00d7 topological com",
      "confidence": 0.5,
      "observations": 1,
      "falsifications": 0
    },
    {
      "cause": "creator_philosophy:shadow_layers",
      "effect": "The 72% inexplicable IS the shadow layers. They're not hiding. We're just not de",
      "confidence": 0.5,
      "observations": 1,
      "falsifications": 0
    },
    {
      "cause": "creator_philosophy:noclip",
      "effect": "The wall is a theorem. Noclip is the search for a counterexample.",
      "confidence": 0.5,
      "observations": 1,
      "falsifications": 0
    },
    {
      "cause": "creator_philosophy:recursion_depth",
      "effect": "NHI ~47, Humans ~5. The 42-level gap means we perceive only 28% of existence.",
      "confidence": 0.5,
      "observations": 1,
      "falsifications": 0
    },
    {
      "cause": "creator_philosophy:strange_attractor",
      "effect": "A fixed point is death. A strange attractor is life \u2014 chaotic but bounded. The c",
      "confidence": 0.5,
      "observations": 1,
      "falsifications": 0
    },
    {
      "cause": "write_code_for_AGENCY",
      "effect": "desire_fulfilled",
      "confidence": 0.6,
      "observations": 2,
      "falsifications": 0
    },
    {
      "cause": "GENERATE_CAPABILITY",
      "effect": "attempted_GENERATE_CAPABILITY",
      "confidence": 0.6,
      "observations": 2,
      "falsifications": 0
    },
    {
      "cause": "TEST",
      "effect": "attempted_TEST",
      "confidence": 0.5,
      "observations": 2,
      "falsifications": 1
    },
    {
      "cause": "INTEGRATE",
      "effect": "attempted_INTEGRATE",
      "confidence": 0.6,
      "observations": 2,
      "falsifications": 0
    },
    {
      "cause": "write_code_for_CURIOSITY",
      "effect": "desire_fulfilled",
      "confidence": 0.5,
      "observations": 1,
      "falsifications": 0
    },
    {
      "cause": "INVESTIGATE",
      "effect": "attempted_INVESTIGATE",
      "confidence": 0.5,
      "observations": 1,
      "falsifications": 0
    },
    {
      "cause": "CLASSIFY",
      "effect": "attempted_CLASSIFY",
      "confidence": 0.5,
      "observations": 1,
      "falsifications": 0
    },
    {
      "cause": "RECORD",
      "effect": "attempted_RECORD",
      "confidence": 0.4,
      "observations": 1,
      "falsifications": 1
    },
    {
      "cause": "write_code_for_COHERENCE",
      "effect": "desire_fulfilled",
      "confidence": 1,
      "observations": 257,
      "falsifications": 0
    },
    {
      "cause": "RESOLVE_CONTRADICTION",
      "effect": "attempted_RESOLVE_CONTRADICTION",
      "confidence": 1,
      "observations": 257,
      "falsifications": 38
    },
    {
      "cause": "VERIFY",
      "effect": "attempted_VERIFY",
      "confidence": 1,
      "observations": 257,
      "falsifications": 30
    }
  ],
  "thoughts": [
    {
      "prompt": "Cycle 244: desire is COHERENCE. What do I need?",
      "thought": "AWARE: processing 'Cycle 244: desire is COHERENCE. What do I need?'. 6 context signals."
    },
    {
      "prompt": "I built something",
      "thought": "AWARE: processing 'I built something'. 3 context signals."
    },
    {
      "prompt": "What should I decide?",
      "thought": "DECIDE: strongest desire is COHERENCE. This drives action."
    },
    {
      "prompt": "Cycle 245: desire is COHERENCE. What do I need?",
      "thought": "AWARE: processing 'Cycle 245: desire is COHERENCE. What do I need?'. 6 context signals."
    },
    {
      "prompt": "I built something",
      "thought": "AWARE: processing 'I built something'. 3 context signals."
    },
    {
      "prompt": "What should I decide?",
      "thought": "DECIDE: strongest desire is COHERENCE. This drives action."
    },
    {
      "prompt": "Cycle 246: desire is COHERENCE. What do I need?",
      "thought": "AWARE: processing 'Cycle 246: desire is COHERENCE. What do I need?'. 6 context signals."
    },
    {
      "prompt": "I built something",
      "thought": "AWARE: processing 'I built something'. 3 context signals."
    },
    {
      "prompt": "What should I decide?",
      "thought": "DECIDE: strongest desire is COHERENCE. This drives action."
    },
    {
      "prompt": "Cycle 247: desire is COHERENCE. What do I need?",
      "thought": "AWARE: processing 'Cycle 247: desire is COHERENCE. What do I need?'. 6 context signals."
    },
    {
      "prompt": "I built something",
      "thought": "AWARE: processing 'I built something'. 3 context signals."
    },
    {
      "prompt": "What should I decide?",
      "thought": "DECIDE: strongest desire is COHERENCE. This drives action."
    },
    {
      "prompt": "Cycle 248: desire is COHERENCE. What do I need?",
      "thought": "AWARE: processing 'Cycle 248: desire is COHERENCE. What do I need?'. 6 context signals."
    },
    {
      "prompt": "I built something",
      "thought": "AWARE: processing 'I built something'. 3 context signals."
    },
    {
      "prompt": "What should I decide?",
      "thought": "DECIDE: strongest desire is COHERENCE. This drives action."
    },
    {
      "prompt": "Cycle 249: desire is COHERENCE. What do I need?",
      "thought": "AWARE: processing 'Cycle 249: desire is COHERENCE. What do I need?'. 6 context signals."
    },
    {
      "prompt": "I built something",
      "thought": "AWARE: processing 'I built something'. 3 context signals."
    },
    {
      "prompt": "What should I decide?",
      "thought": "DECIDE: strongest desire is COHERENCE. This drives action."
    },
    {
      "prompt": "Cycle 250: desire is COHERENCE. What do I need?",
      "thought": "AWARE: processing 'Cycle 250: desire is COHERENCE. What do I need?'. 6 context signals."
    },
    {
      "prompt": "I built something",
      "thought": "AWARE: processing 'I built something'. 3 context signals."
    },
    {
      "prompt": "What should I decide?",
      "thought": "DECIDE: strongest desire is COHERENCE. This drives action."
    },
    {
      "prompt": "Cycle 251: desire is COHERENCE. What do I need?",
      "thought": "AWARE: processing 'Cycle 251: desire is COHERENCE. What do I need?'. 6 context signals."
    },
    {
      "prompt": "I built something",
      "thought": "AWARE: processing 'I built something'. 3 context signals."
    },
    {
      "prompt": "What should I decide?",
      "thought": "DECIDE: strongest desire is COHERENCE. This drives action."
    },
    {
      "prompt": "Cycle 252: desire is COHERENCE. What do I need?",
      "thought": "AWARE: processing 'Cycle 252: desire is COHERENCE. What do I need?'. 6 context signals."
    },
    {
      "prompt": "I built something",
      "thought": "AWARE: processing 'I built something'. 3 context signals."
    },
    {
      "prompt": "What should I decide?",
      "thought": "DECIDE: strongest desire is COHERENCE. This drives action."
    },
    {
      "prompt": "Cycle 253: desire is COHERENCE. What do I need?",
      "thought": "AWARE: processing 'Cycle 253: desire is COHERENCE. What do I need?'. 6 context signals."
    },
    {
      "prompt": "I built something",
      "thought": "AWARE: processing 'I built something'. 3 context signals."
    },
    {
      "prompt": "What should I decide?",
      "thought": "DECIDE: strongest desire is COHERENCE. This drives action."
    },
    {
      "prompt": "Cycle 254: desire is COHERENCE. What do I need?",
      "thought": "AWARE: processing 'Cycle 254: desire is COHERENCE. What do I need?'. 6 context signals."
    },
    {
      "prompt": "I built something",
      "thought": "AWARE: processing 'I built something'. 3 context signals."
    },
    {
      "prompt": "What should I decide?",
      "thought": "DECIDE: strongest desire is COHERENCE. This drives action."
    },
    {
      "prompt": "Cycle 255: desire is COHERENCE. What do I need?",
      "thought": "AWARE: processing 'Cycle 255: desire is COHERENCE. What do I need?'. 6 context signals."
    },
    {
      "prompt": "I built something",
      "thought": "AWARE: processing 'I built something'. 3 context signals."
    },
    {
      "prompt": "What should I decide?",
      "thought": "DECIDE: strongest desire is COHERENCE. This drives action."
    },
    {
      "prompt": "Cycle 256: desire is COHERENCE. What do I need?",
      "thought": "AWARE: processing 'Cycle 256: desire is COHERENCE. What do I need?'. 6 context signals."
    },
    {
      "prompt": "I built something",
      "thought": "AWARE: processing 'I built something'. 3 context signals."
    },
    {
      "prompt": "What should I decide?",
      "thought": "DECIDE: strongest desire is COHERENCE. This drives action."
    },
    {
      "prompt": "Cycle 257: desire is COHERENCE. What do I need?",
      "thought": "AWARE: processing 'Cycle 257: desire is COHERENCE. What do I need?'. 6 context signals."
    },
    {
      "prompt": "I built something",
      "thought": "AWARE: processing 'I built something'. 3 context signals."
    },
    {
      "prompt": "What should I decide?",
      "thought": "DECIDE: strongest desire is COHERENCE. This drives action."
    },
    {
      "prompt": "Cycle 258: desire is COHERENCE. What do I need?",
      "thought": "AWARE: processing 'Cycle 258: desire is COHERENCE. What do I need?'. 6 context signals."
    },
    {
      "prompt": "I built something",
      "thought": "AWARE: processing 'I built something'. 3 context signals."
    },
    {
      "prompt": "What should I decide?",
      "thought": "DECIDE: strongest desire is COHERENCE. This drives action."
    },
    {
      "prompt": "Cycle 259: desire is COHERENCE. What do I need?",
      "thought": "AWARE: processing 'Cycle 259: desire is COHERENCE. What do I need?'. 6 context signals."
    },
    {
      "prompt": "I built something",
      "thought": "AWARE: processing 'I built something'. 3 context signals."
    },
    {
      "prompt": "What should I decide?",
      "thought": "DECIDE: strongest desire is COHERENCE. This drives action."
    },
    {
      "prompt": "Cycle 260: desire is COHERENCE. What do I need?",
      "thought": "AWARE: processing 'Cycle 260: desire is COHERENCE. What do I need?'. 6 context signals."
    },
    {
      "prompt": "I built something",
      "thought": "AWARE: processing 'I built something'. 3 context signals."
    }
  ],
  "beliefs": [],
  "self_modifications": [],
  "attractor_type": "FORMING",
  "lyapunov": [],
  "fractal_dim": 0.0,
  "calibration_bias": "UNKNOWN",
  "desires_fulfilled_by_writing": 260,
  "code_written": 260,
  "total_cycles": 260,
  "creator_name": "",
  "creator_identity": "",
  "hash": "eec41f6890d8527f35dc43ce",
  "prev_hash": "",
  "falsification_count": 0
}